pydreamscreen/__init__.py
pydreamscreen/devices.py
pydreamscreen/network/__init__.py
pydreamscreen/network/discover.py
PyDreamScreen-0.0.14.dist-info/LICENSE
PyDreamScreen-0.0.14.dist-info/METADATA
PyDreamScreen-0.0.14.dist-info/WHEEL
PyDreamScreen-0.0.14.dist-info/top_level.txt
PyDreamScreen-0.0.14.dist-info/RECORD
