Metadata-Version: 2.1
Name: PyDreamScreen
Version: 0.0.14
Summary: Python device discovery and manipulation for DreamScreen HD, 4K, and SideKick devices.
Home-page: https://github.com/GregoryDosh/pydreamscreen
Author: Gregory Dosh
Author-email: pypi@gregorydosh.com
License: MIT
Platform: any
Classifier: Intended Audience :: Developers
Classifier: License :: OSI Approved :: MIT License
Classifier: Operating System :: OS Independent
Classifier: Programming Language :: Python
Classifier: Programming Language :: Python :: 3
Classifier: Topic :: Software Development :: Libraries :: Python Modules
Requires-Dist: crc8 (>=0.0.4)
Requires-Dist: netifaces (>=0.10.9)
